mopactools/__init__.py
mopactools/api.py
mopactools/binding.py
mopactools/lib/libiomp5.dylib
mopactools/lib/libmopac.2.dylib
mopactools/lib/libmopac.dylib
mopactools-0.1.1.dist-info/licenses/LICENSE
mopactools-0.1.1.dist-info/METADATA
mopactools-0.1.1.dist-info/WHEEL
mopactools-0.1.1.dist-info/top_level.txt
mopactools-0.1.1.dist-info/RECORD
