Metadata-Version: 2.4
Name: mopactools
Version: 0.1.1
Summary: Productivity tools for MOPAC
Author-email: Jonathan Moussa <jemoussa@vt.edu>
License: Apache-2.0
Project-URL: Homepage, https://github.com/openmopac/mopactools
Project-URL: Documentation, https://openmopac.github.io/mopactools/
Project-URL: Issues, https://github.com/openmopac/mopactools/issues
Classifier: Programming Language :: Python :: 3
Classifier: Operating System :: POSIX :: Linux
Classifier: Operating System :: MacOS
Classifier: Operating System :: Microsoft :: Windows
Classifier: Development Status :: 4 - Beta
Requires-Python: >=3.6
License-File: LICENSE
Requires-Dist: numpy
Requires-Dist: scipy
Requires-Dist: packaging
Dynamic: license-file
